[ { "fields" : { "app_label" : "auth",
        "model" : "permission",
        "name" : "permission"
      },
    "model" : "contenttypes.contenttype",
    "pk" : 1
  },
  { "fields" : { "app_label" : "auth",
        "model" : "group",
        "name" : "group"
      },
    "model" : "contenttypes.contenttype",
    "pk" : 2
  },
  { "fields" : { "app_label" : "auth",
        "model" : "user",
        "name" : "user"
      },
    "model" : "contenttypes.contenttype",
    "pk" : 3
  },
  { "fields" : { "app_label" : "contenttypes",
        "model" : "contenttype",
        "name" : "content type"
      },
    "model" : "contenttypes.contenttype",
    "pk" : 4
  },
  { "fields" : { "app_label" : "sessions",
        "model" : "session",
        "name" : "session"
      },
    "model" : "contenttypes.contenttype",
    "pk" : 5
  },
  { "fields" : { "app_label" : "sites",
        "model" : "site",
        "name" : "site"
      },
    "model" : "contenttypes.contenttype",
    "pk" : 6
  },
  { "fields" : { "app_label" : "admin",
        "model" : "logentry",
        "name" : "log entry"
      },
    "model" : "contenttypes.contenttype",
    "pk" : 7
  },
  { "fields" : { "app_label" : "gallery",
        "model" : "gallerycategory",
        "name" : "gallery category"
      },
    "model" : "contenttypes.contenttype",
    "pk" : 8
  },
  { "fields" : { "app_label" : "gallery",
        "model" : "galleryitem",
        "name" : "gallery item"
      },
    "model" : "contenttypes.contenttype",
    "pk" : 9
  },
  { "fields" : { "app_label" : "gallery",
        "model" : "galleryitemmodifier",
        "name" : "gallery item modifier"
      },
    "model" : "contenttypes.contenttype",
    "pk" : 10
  },
  { "fields" : { "expire_date" : "2013-06-03T00:03:03.962Z",
        "session_data" : "YjJjMmNhYzQ0ZWQ1ZGEzMGZiNTU4YzFjYjRiNmQ1ZmUzNmI0NTJmNTqAAn1xAShVEl9hdXRoX3VzZXJfYmFja2VuZHECVSlkamFuZ28uY29udHJpYi5hdXRoLmJhY2tlbmRzLk1vZGVsQmFja2VuZHEDVQ1fYXV0aF91c2VyX2lkcQRLAXUu"
      },
    "model" : "sessions.session",
    "pk" : "yzga2fr89prr6hk16babnk8v5qibauk8"
  },
  { "fields" : { "domain" : "example.com",
        "name" : "example.com"
      },
    "model" : "sites.site",
    "pk" : 1
  },
  { "fields" : { "addedOn" : "2013-05-20T00:03:16Z",
        "title" : "Landscapes",
        "updatedOn" : "2013-05-20T00:03:16Z"
      },
    "model" : "gallery.gallerycategory",
    "pk" : 1
  },
  { "fields" : { "addedOn" : "2013-05-20T00:03:50Z",
        "title" : "Floral Arrangements",
        "updatedOn" : "2013-05-20T00:03:50Z"
      },
    "model" : "gallery.gallerycategory",
    "pk" : 2
  },
  { "fields" : { "addedOn" : "2013-05-20T00:04:06Z",
        "title" : "Other Designs",
        "updatedOn" : "2013-05-20T00:04:06Z"
      },
    "model" : "gallery.gallerycategory",
    "pk" : 3
  },
  { "fields" : { "addedOn" : "2013-05-20T00:07:28Z",
        "category" : 1,
        "cover" : "img/gallery/art/151-winter%20landscape-w-sm1.png",
        "description" : "I had an incredible time making this winter landscape. I used pastels covered with corn husks for the sky and was very pleased with the contrast of the mountains in the background. The cabin with smoke rising from the chimney made me want to enter it and sit by the fire.  I could clearly imagine sitting in the cabin and enjoying the landscape and oneness with nature from a window. It definitely brought out my oneness with nature.  I hope it does the same for you!\r\n\r\nBotanical materials included poplar, blackberry, day lilly, lilly of the valley and assorted Fall leaves; straw, corn husks, fern, hydrangea stems, onion skins, cosmos, cotton and birch bark. ",
        "frame_image" : "img/gallery/art/151-winter%20landscape-w-sm1.png",
        "image" : "img/gallery/art/151-winter%20landscape-w-sm1.png",
        "item_num" : 151,
        "title" : "A winter landscape",
        "updatedOn" : "2013-05-20T00:07:28Z"
      },
    "model" : "gallery.galleryitem",
    "pk" : 1
  },
  { "fields" : { "addedOn" : "2013-05-20T01:00:00Z",
        "category" : 1,
        "cover" : "img/gallery/art/149-Golden-Sunset-w-sm2.png",
        "description" : "coming soon",
        "frame_image" : "img/gallery/art/149-Golden-Sunset-w-sm2.png",
        "image" : "img/gallery/art/149-Golden-Sunset-w-sm2.png",
        "item_num" : 149,
        "title" : "Golden Sunset",
        "updatedOn" : "2013-05-20T01:00:00Z"
      },
    "model" : "gallery.galleryitem",
    "pk" : 2
  },
  { "fields" : { "addedOn" : "2013-05-20T01:01:04Z",
        "category" : 1,
        "cover" : "img/gallery/art/119-My-Mothers-Garden-w-sm1.png",
        "description" : "coming soon",
        "frame_image" : "img/gallery/art/119-My-Mothers-Garden-w-sm1.png",
        "image" : "img/gallery/art/119-My-Mothers-Garden-w-sm1.png",
        "item_num" : 119,
        "title" : "My Mother's Day Garden",
        "updatedOn" : "2013-05-20T01:01:04Z"
      },
    "model" : "gallery.galleryitem",
    "pk" : 3
  },
  { "fields" : { "addedOn" : "2013-05-20T01:01:58Z",
        "category" : 1,
        "cover" : "img/gallery/art/118-Memories-Past-w-sm1.png",
        "description" : "coming soon",
        "frame_image" : "img/gallery/art/118-Memories-Past-w-sm1.png",
        "image" : "img/gallery/art/118-Memories-Past-w-sm1.png",
        "item_num" : 118,
        "title" : "Memories Past",
        "updatedOn" : "2013-05-20T01:01:58Z"
      },
    "model" : "gallery.galleryitem",
    "pk" : 4
  },
  { "fields" : { "addedOn" : "2013-05-20T01:02:35Z",
        "category" : 1,
        "cover" : "img/gallery/art/138-Regal-Rooster-w-sm2.png",
        "description" : "coming soon",
        "frame_image" : "img/gallery/art/138-Regal-Rooster-w-sm2.png",
        "image" : "img/gallery/art/138-Regal-Rooster-w-sm2.png",
        "item_num" : 138,
        "title" : "Regal Rooster",
        "updatedOn" : "2013-05-20T01:02:35Z"
      },
    "model" : "gallery.galleryitem",
    "pk" : 5
  },
  { "fields" : { "addedOn" : "2013-05-20T01:04:23Z",
        "category" : 1,
        "cover" : "img/gallery/art/93-Enchanted-Garden-w-sm1.png",
        "description" : "coming soon",
        "frame_image" : "img/gallery/art/93-Enchanted-Garden-w-sm1.png",
        "image" : "img/gallery/art/93-Enchanted-Garden-w-sm1.png",
        "item_num" : 93,
        "title" : "Enchanted Garden",
        "updatedOn" : "2013-05-20T01:04:23Z"
      },
    "model" : "gallery.galleryitem",
    "pk" : 6
  },
  { "fields" : { "addedOn" : "2013-05-20T01:05:11Z",
        "category" : 1,
        "cover" : "img/gallery/art/115-Autumn-splender-w-sm1.png",
        "description" : "coming soon",
        "frame_image" : "img/gallery/art/115-Autumn-splender-w-sm1.png",
        "image" : "img/gallery/art/115-Autumn-splender-w-sm1.png",
        "item_num" : 115,
        "title" : "Autumn Splender",
        "updatedOn" : "2013-05-20T01:05:11Z"
      },
    "model" : "gallery.galleryitem",
    "pk" : 7
  },
  { "fields" : { "addedOn" : "2013-05-20T01:06:03Z",
        "category" : 1,
        "cover" : "img/gallery/art/150-Summer Birch Trees-w-sm1.png",
        "description" : "coming soon",
        "frame_image" : "img/gallery/art/150-Summer Birch Trees-w-sm1.png",
        "image" : "img/gallery/art/150-Summer Birch Trees-w-sm1.png",
        "item_num" : 150,
        "title" : "Summer Birch Trees",
        "updatedOn" : "2013-05-20T01:06:03Z"
      },
    "model" : "gallery.galleryitem",
    "pk" : 8
  },
  { "fields" : { "addedOn" : "2013-05-20T01:06:31Z",
        "category" : 1,
        "cover" : "img/gallery/art/113-Tropical-Garden-w-sm1.png",
        "description" : "coming soon",
        "frame_image" : "img/gallery/art/113-Tropical-Garden-w-sm1.png",
        "image" : "img/gallery/art/113-Tropical-Garden-w-sm1.png",
        "item_num" : 113,
        "title" : "Tropical Garden",
        "updatedOn" : "2013-05-20T01:06:31Z"
      },
    "model" : "gallery.galleryitem",
    "pk" : 9
  },
  { "fields" : { "addedOn" : "2013-05-20T01:07:22Z",
        "category" : 2,
        "cover" : "img/gallery/art/142-Fall-Wagon-of-Flowers-w-sm1.png",
        "description" : "coming soon",
        "frame_image" : "img/gallery/art/142-Fall-Wagon-of-Flowers-w-sm1.png",
        "image" : "img/gallery/art/142-Fall-Wagon-of-Flowers-w-sm1.png",
        "item_num" : 142,
        "title" : "Fall Wagon of Flowers",
        "updatedOn" : "2013-05-20T01:07:22Z"
      },
    "model" : "gallery.galleryitem",
    "pk" : 10
  },
  { "fields" : { "addedOn" : "2013-05-20T01:58:03Z",
        "category" : 2,
        "cover" : "img/gallery/art/157-Beehive Basket2-w-sm1.png",
        "description" : "coming soon",
        "frame_image" : "img/gallery/art/157-Beehive Basket2-w-sm1.png",
        "image" : "img/gallery/art/157-Beehive Basket2-w-sm1.png",
        "item_num" : 157,
        "title" : "Behhive Basket",
        "updatedOn" : "2013-05-20T01:58:03Z"
      },
    "model" : "gallery.galleryitem",
    "pk" : 11
  },
  { "fields" : { "addedOn" : "2013-05-20T01:58:27Z",
        "category" : 2,
        "cover" : "img/gallery/art/140-wheelbarrow-w-sm1.png",
        "description" : "coming soon",
        "frame_image" : "img/gallery/art/140-wheelbarrow-w-sm1.png",
        "image" : "img/gallery/art/140-wheelbarrow-w-sm1.png",
        "item_num" : 140,
        "title" : "Wheelbarrow",
        "updatedOn" : "2013-05-20T01:58:27Z"
      },
    "model" : "gallery.galleryitem",
    "pk" : 12
  },
  { "fields" : { "addedOn" : "2013-05-20T01:58:57Z",
        "category" : 2,
        "cover" : "img/gallery/art/123-Magnolia-and-Lace-w-sm1.png",
        "description" : "coming soon",
        "frame_image" : "img/gallery/art/123-Magnolia-and-Lace-w-sm1.png",
        "image" : "img/gallery/art/123-Magnolia-and-Lace-w-sm1.png",
        "item_num" : 123,
        "title" : "Magnolia and Lace",
        "updatedOn" : "2013-05-20T01:58:57Z"
      },
    "model" : "gallery.galleryitem",
    "pk" : 13
  },
  { "fields" : { "addedOn" : "2013-05-20T01:59:56Z",
        "category" : 2,
        "cover" : "img/gallery/art/117-Glorious-Daffodils-w-sm1.png",
        "description" : "coming soon",
        "frame_image" : "img/gallery/art/117-Glorious-Daffodils-w-sm1.png",
        "image" : "img/gallery/art/117-Glorious-Daffodils-w-sm1.png",
        "item_num" : 117,
        "title" : "Glorious Daffodils",
        "updatedOn" : "2013-05-20T01:59:56Z"
      },
    "model" : "gallery.galleryitem",
    "pk" : 14
  },
  { "fields" : { "addedOn" : "2013-05-20T02:00:27Z",
        "category" : 2,
        "cover" : "img/gallery/art/107-Follow-the-Light-w1.png",
        "description" : "coming soon",
        "frame_image" : "img/gallery/art/107-Follow-the-Light-w1.png",
        "image" : "img/gallery/art/107-Follow-the-Light-w1.png",
        "item_num" : 107,
        "title" : "Follow the Light",
        "updatedOn" : "2013-05-20T02:00:27Z"
      },
    "model" : "gallery.galleryitem",
    "pk" : 15
  },
  { "fields" : { "addedOn" : "2013-05-20T02:00:56Z",
        "category" : 3,
        "cover" : "img/gallery/art/145-Natures-Dance-w-sm1.png",
        "description" : "coming soon",
        "frame_image" : "img/gallery/art/145-Natures-Dance-w-sm1.png",
        "image" : "img/gallery/art/145-Natures-Dance-w-sm1.png",
        "item_num" : 145,
        "title" : "Nature's Dance",
        "updatedOn" : "2013-05-20T02:00:56Z"
      },
    "model" : "gallery.galleryitem",
    "pk" : 16
  },
  { "fields" : { "addedOn" : "2013-05-20T02:01:28Z",
        "category" : 3,
        "cover" : "img/gallery/art/159-Garden Visitor-w-sm1.png",
        "description" : "coming soon",
        "frame_image" : "img/gallery/art/159-Garden Visitor-w-sm1.png",
        "image" : "img/gallery/art/159-Garden Visitor-w-sm1.png",
        "item_num" : 159,
        "title" : "Garden Visitor",
        "updatedOn" : "2013-05-20T02:01:28Z"
      },
    "model" : "gallery.galleryitem",
    "pk" : 17
  },
  { "fields" : { "item" : 1,
        "order" : 10,
        "title" : "Size of Art",
        "value" : "11\" x 14\""
      },
    "model" : "gallery.galleryitemmodifier",
    "pk" : 1
  },
  { "fields" : { "item" : 1,
        "order" : 10,
        "title" : "Framed Size",
        "value" : "16\" x 20\""
      },
    "model" : "gallery.galleryitemmodifier",
    "pk" : 2
  },
  { "fields" : { "item" : 1,
        "order" : 10,
        "title" : "Original",
        "value" : "Yes"
      },
    "model" : "gallery.galleryitemmodifier",
    "pk" : 3
  },
  { "fields" : { "item" : 1,
        "order" : 10,
        "title" : "Price",
        "value" : "$195"
      },
    "model" : "gallery.galleryitemmodifier",
    "pk" : 4
  },
  { "fields" : { "codename" : "add_permission",
        "content_type" : 1,
        "name" : "Can add permission"
      },
    "model" : "auth.permission",
    "pk" : 1
  },
  { "fields" : { "codename" : "change_permission",
        "content_type" : 1,
        "name" : "Can change permission"
      },
    "model" : "auth.permission",
    "pk" : 2
  },
  { "fields" : { "codename" : "delete_permission",
        "content_type" : 1,
        "name" : "Can delete permission"
      },
    "model" : "auth.permission",
    "pk" : 3
  },
  { "fields" : { "codename" : "add_group",
        "content_type" : 2,
        "name" : "Can add group"
      },
    "model" : "auth.permission",
    "pk" : 4
  },
  { "fields" : { "codename" : "change_group",
        "content_type" : 2,
        "name" : "Can change group"
      },
    "model" : "auth.permission",
    "pk" : 5
  },
  { "fields" : { "codename" : "delete_group",
        "content_type" : 2,
        "name" : "Can delete group"
      },
    "model" : "auth.permission",
    "pk" : 6
  },
  { "fields" : { "codename" : "add_user",
        "content_type" : 3,
        "name" : "Can add user"
      },
    "model" : "auth.permission",
    "pk" : 7
  },
  { "fields" : { "codename" : "change_user",
        "content_type" : 3,
        "name" : "Can change user"
      },
    "model" : "auth.permission",
    "pk" : 8
  },
  { "fields" : { "codename" : "delete_user",
        "content_type" : 3,
        "name" : "Can delete user"
      },
    "model" : "auth.permission",
    "pk" : 9
  },
  { "fields" : { "codename" : "add_contenttype",
        "content_type" : 4,
        "name" : "Can add content type"
      },
    "model" : "auth.permission",
    "pk" : 10
  },
  { "fields" : { "codename" : "change_contenttype",
        "content_type" : 4,
        "name" : "Can change content type"
      },
    "model" : "auth.permission",
    "pk" : 11
  },
  { "fields" : { "codename" : "delete_contenttype",
        "content_type" : 4,
        "name" : "Can delete content type"
      },
    "model" : "auth.permission",
    "pk" : 12
  },
  { "fields" : { "codename" : "add_session",
        "content_type" : 5,
        "name" : "Can add session"
      },
    "model" : "auth.permission",
    "pk" : 13
  },
  { "fields" : { "codename" : "change_session",
        "content_type" : 5,
        "name" : "Can change session"
      },
    "model" : "auth.permission",
    "pk" : 14
  },
  { "fields" : { "codename" : "delete_session",
        "content_type" : 5,
        "name" : "Can delete session"
      },
    "model" : "auth.permission",
    "pk" : 15
  },
  { "fields" : { "codename" : "add_site",
        "content_type" : 6,
        "name" : "Can add site"
      },
    "model" : "auth.permission",
    "pk" : 16
  },
  { "fields" : { "codename" : "change_site",
        "content_type" : 6,
        "name" : "Can change site"
      },
    "model" : "auth.permission",
    "pk" : 17
  },
  { "fields" : { "codename" : "delete_site",
        "content_type" : 6,
        "name" : "Can delete site"
      },
    "model" : "auth.permission",
    "pk" : 18
  },
  { "fields" : { "codename" : "add_logentry",
        "content_type" : 7,
        "name" : "Can add log entry"
      },
    "model" : "auth.permission",
    "pk" : 19
  },
  { "fields" : { "codename" : "change_logentry",
        "content_type" : 7,
        "name" : "Can change log entry"
      },
    "model" : "auth.permission",
    "pk" : 20
  },
  { "fields" : { "codename" : "delete_logentry",
        "content_type" : 7,
        "name" : "Can delete log entry"
      },
    "model" : "auth.permission",
    "pk" : 21
  },
  { "fields" : { "codename" : "add_gallerycategory",
        "content_type" : 8,
        "name" : "Can add gallery category"
      },
    "model" : "auth.permission",
    "pk" : 22
  },
  { "fields" : { "codename" : "change_gallerycategory",
        "content_type" : 8,
        "name" : "Can change gallery category"
      },
    "model" : "auth.permission",
    "pk" : 23
  },
  { "fields" : { "codename" : "delete_gallerycategory",
        "content_type" : 8,
        "name" : "Can delete gallery category"
      },
    "model" : "auth.permission",
    "pk" : 24
  },
  { "fields" : { "codename" : "add_galleryitem",
        "content_type" : 9,
        "name" : "Can add gallery item"
      },
    "model" : "auth.permission",
    "pk" : 25
  },
  { "fields" : { "codename" : "change_galleryitem",
        "content_type" : 9,
        "name" : "Can change gallery item"
      },
    "model" : "auth.permission",
    "pk" : 26
  },
  { "fields" : { "codename" : "delete_galleryitem",
        "content_type" : 9,
        "name" : "Can delete gallery item"
      },
    "model" : "auth.permission",
    "pk" : 27
  },
  { "fields" : { "codename" : "add_galleryitemmodifier",
        "content_type" : 10,
        "name" : "Can add gallery item modifier"
      },
    "model" : "auth.permission",
    "pk" : 28
  },
  { "fields" : { "codename" : "change_galleryitemmodifier",
        "content_type" : 10,
        "name" : "Can change gallery item modifier"
      },
    "model" : "auth.permission",
    "pk" : 29
  },
  { "fields" : { "codename" : "delete_galleryitemmodifier",
        "content_type" : 10,
        "name" : "Can delete gallery item modifier"
      },
    "model" : "auth.permission",
    "pk" : 30
  },
  { "fields" : { "date_joined" : "2013-05-20T00:02:40.006Z",
        "email" : "arrong@gmail.com",
        "first_name" : "",
        "groups" : [  ],
        "is_active" : true,
        "is_staff" : true,
        "is_superuser" : true,
        "last_login" : "2013-05-20T00:03:03.960Z",
        "last_name" : "",
        "password" : "pbkdf2_sha256$10000$ckr0TaOhXusf$sjudH7UrFK/ACfJM5250kCovQqoOKG+4+QWbbG/k9E0=",
        "user_permissions" : [  ],
        "username" : "arron"
      },
    "model" : "auth.user",
    "pk" : 1
  },
  { "fields" : { "action_flag" : 1,
        "action_time" : "2013-05-20T00:03:50.670Z",
        "change_message" : "",
        "content_type" : 8,
        "object_id" : "1",
        "object_repr" : "GalleryCategory object",
        "user" : 1
      },
    "model" : "admin.logentry",
    "pk" : 1
  },
  { "fields" : { "action_flag" : 1,
        "action_time" : "2013-05-20T00:04:02.853Z",
        "change_message" : "",
        "content_type" : 8,
        "object_id" : "2",
        "object_repr" : "GalleryCategory object",
        "user" : 1
      },
    "model" : "admin.logentry",
    "pk" : 2
  },
  { "fields" : { "action_flag" : 1,
        "action_time" : "2013-05-20T00:04:16.577Z",
        "change_message" : "",
        "content_type" : 8,
        "object_id" : "3",
        "object_repr" : "GalleryCategory object",
        "user" : 1
      },
    "model" : "admin.logentry",
    "pk" : 3
  },
  { "fields" : { "action_flag" : 1,
        "action_time" : "2013-05-20T00:10:59.939Z",
        "change_message" : "",
        "content_type" : 9,
        "object_id" : "1",
        "object_repr" : "A winter landscape",
        "user" : 1
      },
    "model" : "admin.logentry",
    "pk" : 4
  },
  { "fields" : { "action_flag" : 1,
        "action_time" : "2013-05-20T00:12:09.139Z",
        "change_message" : "",
        "content_type" : 10,
        "object_id" : "1",
        "object_repr" : "Size of Art=11\" x 14\"",
        "user" : 1
      },
    "model" : "admin.logentry",
    "pk" : 5
  },
  { "fields" : { "action_flag" : 1,
        "action_time" : "2013-05-20T00:12:31.334Z",
        "change_message" : "",
        "content_type" : 10,
        "object_id" : "2",
        "object_repr" : "Framed Size=16\" x 20\"",
        "user" : 1
      },
    "model" : "admin.logentry",
    "pk" : 6
  },
  { "fields" : { "action_flag" : 1,
        "action_time" : "2013-05-20T00:13:02.063Z",
        "change_message" : "",
        "content_type" : 10,
        "object_id" : "3",
        "object_repr" : "Original=Yes",
        "user" : 1
      },
    "model" : "admin.logentry",
    "pk" : 7
  },
  { "fields" : { "action_flag" : 1,
        "action_time" : "2013-05-20T00:13:18.017Z",
        "change_message" : "",
        "content_type" : 10,
        "object_id" : "4",
        "object_repr" : "Price=$195",
        "user" : 1
      },
    "model" : "admin.logentry",
    "pk" : 8
  },
  { "fields" : { "action_flag" : 1,
        "action_time" : "2013-05-20T01:01:04.492Z",
        "change_message" : "",
        "content_type" : 9,
        "object_id" : "2",
        "object_repr" : "Golden Sunset",
        "user" : 1
      },
    "model" : "admin.logentry",
    "pk" : 9
  },
  { "fields" : { "action_flag" : 1,
        "action_time" : "2013-05-20T01:01:58.865Z",
        "change_message" : "",
        "content_type" : 9,
        "object_id" : "3",
        "object_repr" : "My Mother's Day Garden",
        "user" : 1
      },
    "model" : "admin.logentry",
    "pk" : 10
  },
  { "fields" : { "action_flag" : 1,
        "action_time" : "2013-05-20T01:02:35.402Z",
        "change_message" : "",
        "content_type" : 9,
        "object_id" : "4",
        "object_repr" : "Memories Past",
        "user" : 1
      },
    "model" : "admin.logentry",
    "pk" : 11
  },
  { "fields" : { "action_flag" : 1,
        "action_time" : "2013-05-20T01:04:23.868Z",
        "change_message" : "",
        "content_type" : 9,
        "object_id" : "5",
        "object_repr" : "Regal Rooster",
        "user" : 1
      },
    "model" : "admin.logentry",
    "pk" : 12
  },
  { "fields" : { "action_flag" : 1,
        "action_time" : "2013-05-20T01:05:11.868Z",
        "change_message" : "",
        "content_type" : 9,
        "object_id" : "6",
        "object_repr" : "Enchanted Garden",
        "user" : 1
      },
    "model" : "admin.logentry",
    "pk" : 13
  },
  { "fields" : { "action_flag" : 1,
        "action_time" : "2013-05-20T01:06:03.754Z",
        "change_message" : "",
        "content_type" : 9,
        "object_id" : "7",
        "object_repr" : "Autumn Splender",
        "user" : 1
      },
    "model" : "admin.logentry",
    "pk" : 14
  },
  { "fields" : { "action_flag" : 1,
        "action_time" : "2013-05-20T01:06:31.643Z",
        "change_message" : "",
        "content_type" : 9,
        "object_id" : "8",
        "object_repr" : "Summer Birch Trees",
        "user" : 1
      },
    "model" : "admin.logentry",
    "pk" : 15
  },
  { "fields" : { "action_flag" : 1,
        "action_time" : "2013-05-20T01:07:22.289Z",
        "change_message" : "",
        "content_type" : 9,
        "object_id" : "9",
        "object_repr" : "Tropical Garden",
        "user" : 1
      },
    "model" : "admin.logentry",
    "pk" : 16
  },
  { "fields" : { "action_flag" : 1,
        "action_time" : "2013-05-20T01:58:03.714Z",
        "change_message" : "",
        "content_type" : 9,
        "object_id" : "10",
        "object_repr" : "Fall Wagon of Flowers",
        "user" : 1
      },
    "model" : "admin.logentry",
    "pk" : 17
  },
  { "fields" : { "action_flag" : 1,
        "action_time" : "2013-05-20T01:58:27.153Z",
        "change_message" : "",
        "content_type" : 9,
        "object_id" : "11",
        "object_repr" : "Behhive Basket",
        "user" : 1
      },
    "model" : "admin.logentry",
    "pk" : 18
  },
  { "fields" : { "action_flag" : 1,
        "action_time" : "2013-05-20T01:58:57.686Z",
        "change_message" : "",
        "content_type" : 9,
        "object_id" : "12",
        "object_repr" : "Wheelbarrow",
        "user" : 1
      },
    "model" : "admin.logentry",
    "pk" : 19
  },
  { "fields" : { "action_flag" : 1,
        "action_time" : "2013-05-20T01:59:56.533Z",
        "change_message" : "",
        "content_type" : 9,
        "object_id" : "13",
        "object_repr" : "Magnolia and Lace",
        "user" : 1
      },
    "model" : "admin.logentry",
    "pk" : 20
  },
  { "fields" : { "action_flag" : 1,
        "action_time" : "2013-05-20T02:00:27.665Z",
        "change_message" : "",
        "content_type" : 9,
        "object_id" : "14",
        "object_repr" : "Glorious Daffodils",
        "user" : 1
      },
    "model" : "admin.logentry",
    "pk" : 21
  },
  { "fields" : { "action_flag" : 1,
        "action_time" : "2013-05-20T02:00:55.989Z",
        "change_message" : "",
        "content_type" : 9,
        "object_id" : "15",
        "object_repr" : "Follow the Light",
        "user" : 1
      },
    "model" : "admin.logentry",
    "pk" : 22
  },
  { "fields" : { "action_flag" : 1,
        "action_time" : "2013-05-20T02:01:28.617Z",
        "change_message" : "",
        "content_type" : 9,
        "object_id" : "16",
        "object_repr" : "Nature's Dance",
        "user" : 1
      },
    "model" : "admin.logentry",
    "pk" : 23
  },
  { "fields" : { "action_flag" : 1,
        "action_time" : "2013-05-20T02:01:56.101Z",
        "change_message" : "",
        "content_type" : 9,
        "object_id" : "17",
        "object_repr" : "Garden Visitor",
        "user" : 1
      },
    "model" : "admin.logentry",
    "pk" : 24
  }
]